pymusiclooper/__init__.py
pymusiclooper/__main__.py
pymusiclooper/analysis.py
pymusiclooper/audio.py
pymusiclooper/cli.py
pymusiclooper/console.py
pymusiclooper/core.py
pymusiclooper/exceptions.py
pymusiclooper/handler.py
pymusiclooper/playback.py
pymusiclooper/utils.py
pymusiclooper/youtube.py
pymusiclooper-3.5.1.dist-info/METADATA
pymusiclooper-3.5.1.dist-info/WHEEL
pymusiclooper-3.5.1.dist-info/entry_points.txt
pymusiclooper-3.5.1.dist-info/licenses/LICENSE
pymusiclooper-3.5.1.dist-info/RECORD
