Metadata-Version: 2.4
Name: pymusiclooper
Version: 3.5.1
Summary: Repeat music endlessly and create seamless music loops, with play/export/tagging support.
Project-URL: Repository, https://github.com/arkrow/PyMusicLooper
Project-URL: Changelog, https://github.com/arkrow/PyMusicLooper/blob/master/CHANGELOG.md
Author-email: arkrow <arkrow@protonmail.com>
License-Expression: MIT
License-File: LICENSE
Classifier: Development Status :: 5 - Production/Stable
Classifier: Environment :: Console
Classifier: License :: OSI Approved :: MIT License
Classifier: Operating System :: OS Independent
Classifier: Programming Language :: Python
Classifier: Programming Language :: Python :: 3 :: Only
Classifier: Programming Language :: Python :: 3.10
Classifier: Programming Language :: Python :: 3.11
Classifier: Programming Language :: Python :: 3.12
Classifier: Programming Language :: Python :: 3.13
Classifier: Topic :: Multimedia :: Sound/Audio
Classifier: Topic :: Multimedia :: Sound/Audio :: Analysis
Requires-Python: ~=3.10
Requires-Dist: click-option-group<0.6,>=0.5.6
Requires-Dist: click-params<0.6,>=0.5.0
Requires-Dist: lazy-loader>=0.3
Requires-Dist: librosa<0.12.0,>=0.11.0
Requires-Dist: numba>=0.59.1
Requires-Dist: numpy>=1.25.0
Requires-Dist: pytaglib<4,>=3.0.0
Requires-Dist: rich-click<2,>=1.8.0
Requires-Dist: rich>=13.4.2
Requires-Dist: sounddevice>=0.5.0
Requires-Dist: soundfile>=0.12.1
Requires-Dist: yt-dlp>=2025.01.26
